repare/__init__.py
repare/main.py
repare/pedigree.py
repare/pedigree_reconstructor.py
repare-0.1.4.dist-info/licenses/LICENSE
repare-0.1.4.dist-info/METADATA
repare-0.1.4.dist-info/WHEEL
repare-0.1.4.dist-info/entry_points.txt
repare-0.1.4.dist-info/top_level.txt
repare-0.1.4.dist-info/RECORD
