Metadata-Version: 2.4
Name: repare
Version: 0.1.4
Summary: Reconstruct (ancient) pedigrees from pairwise kinship relations.
Author-email: Edward Huang <edwardhuangc@gmail.com>
License-Expression: MIT
Project-URL: Source, https://github.com/ehuangc/repare
Requires-Python: >=3.10
License-File: LICENSE
Requires-Dist: matplotlib
Requires-Dist: networkx
Requires-Dist: pandas
Requires-Dist: tqdm
Provides-Extra: benchmark
Requires-Dist: scikit-learn; extra == "benchmark"
Requires-Dist: seaborn; extra == "benchmark"
Provides-Extra: plot
Requires-Dist: pygraphviz; extra == "plot"
Dynamic: license-file
